{
  "total_callers": 62,
  "callers": [
    {
      "caller": "Brook",
      "totalCalls": 831,
      "uniqueTokens": 648,
      "totalTrades": 486,
      "winRate": 47.73662551440329,
      "winningTrades": 232,
      "losingTrades": 254,
      "avgPnlPerTrade": 4.7169146125341825,
      "finalPortfolio": 834.7583377937069,
      "compoundFactor": 8.347583377937069,
      "simpleFinalPortfolio": 329.2420501691613,
      "simpleReturnPercent": 229.2420501691613,
      "initialPortfolio": 100
    },
    {
      "caller": "Austic",
      "totalCalls": 224,
      "uniqueTokens": 222,
      "totalTrades": 193,
      "winRate": 49.22279792746114,
      "winningTrades": 95,
      "losingTrades": 98,
      "avgPnlPerTrade": 6.881346248108993,
      "finalPortfolio": 346.22079533169915,
      "compoundFactor": 3.4622079533169914,
      "simpleFinalPortfolio": 232.8099825885035,
      "simpleReturnPercent": 132.8099825885035,
      "initialPortfolio": 100
    },
    {
      "caller": "Brook Giga I verify @BrookCalls",
      "totalCalls": 511,
      "uniqueTokens": 392,
      "totalTrades": 276,
      "winRate": 46.3768115942029,
      "winningTrades": 128,
      "losingTrades": 148,
      "avgPnlPerTrade": 4.113574930762226,
      "finalPortfolio": 284.03804019844193,
      "compoundFactor": 2.840380401984419,
      "simpleFinalPortfolio": 213.5346680890374,
      "simpleReturnPercent": 113.53466808903741,
      "initialPortfolio": 100
    },
    {
      "caller": "meta maxist",
      "totalCalls": 222,
      "uniqueTokens": 219,
      "totalTrades": 187,
      "winRate": 45.98930481283423,
      "winningTrades": 86,
      "losingTrades": 101,
      "avgPnlPerTrade": 4.734206859756034,
      "finalPortfolio": 230.3077754288869,
      "compoundFactor": 2.303077754288869,
      "simpleFinalPortfolio": 188.5296682774378,
      "simpleReturnPercent": 88.5296682774378,
      "initialPortfolio": 100
    },
    {
      "caller": "Croz",
      "totalCalls": 185,
      "uniqueTokens": 181,
      "totalTrades": 151,
      "winRate": 45.033112582781456,
      "winningTrades": 68,
      "losingTrades": 83,
      "avgPnlPerTrade": 5.464823750338066,
      "finalPortfolio": 211.79705204158887,
      "compoundFactor": 2.1179705204158887,
      "simpleFinalPortfolio": 182.51883863010485,
      "simpleReturnPercent": 82.51883863010485,
      "initialPortfolio": 100
    },
    {
      "caller": "Meechi",
      "totalCalls": 1,
      "uniqueTokens": 1,
      "totalTrades": 1,
      "winRate": 100,
      "winningTrades": 1,
      "losingTrades": 0,
      "avgPnlPerTrade": 1050.2554709808837,
      "finalPortfolio": 205.02554709808837,
      "compoundFactor": 2.0502554709808836,
      "simpleFinalPortfolio": 205.02554709808837,
      "simpleReturnPercent": 105.02554709808835,
      "initialPortfolio": 100
    },
    {
      "caller": "exy",
      "totalCalls": 105,
      "uniqueTokens": 103,
      "totalTrades": 69,
      "winRate": 52.17391304347826,
      "winningTrades": 36,
      "losingTrades": 33,
      "avgPnlPerTrade": 10.73896383658936,
      "finalPortfolio": 191.55348533361553,
      "compoundFactor": 1.9155348533361554,
      "simpleFinalPortfolio": 174.09885047246658,
      "simpleReturnPercent": 74.09885047246658,
      "initialPortfolio": 100
    },
    {
      "caller": "davinch",
      "totalCalls": 199,
      "uniqueTokens": 198,
      "totalTrades": 172,
      "winRate": 43.02325581395349,
      "winningTrades": 74,
      "losingTrades": 98,
      "avgPnlPerTrade": 3.7493430519042192,
      "finalPortfolio": 182.23807673610665,
      "compoundFactor": 1.8223807673610666,
      "simpleFinalPortfolio": 164.48870049275254,
      "simpleReturnPercent": 64.48870049275254,
      "initialPortfolio": 100
    },
    {
      "caller": "Mistor",
      "totalCalls": 95,
      "uniqueTokens": 91,
      "totalTrades": 72,
      "winRate": 55.55555555555556,
      "winningTrades": 40,
      "losingTrades": 32,
      "avgPnlPerTrade": 8.224428514016159,
      "finalPortfolio": 174.26497387849813,
      "compoundFactor": 1.7426497387849813,
      "simpleFinalPortfolio": 159.21588530091634,
      "simpleReturnPercent": 59.21588530091635,
      "initialPortfolio": 100
    },
    {
      "caller": "TY/ACC",
      "totalCalls": 86,
      "uniqueTokens": 76,
      "totalTrades": 44,
      "winRate": 50,
      "winningTrades": 22,
      "losingTrades": 22,
      "avgPnlPerTrade": 12.337295147810302,
      "finalPortfolio": 165.81623451550146,
      "compoundFactor": 1.6581623451550147,
      "simpleFinalPortfolio": 154.28409865036534,
      "simpleReturnPercent": 54.284098650365344,
      "initialPortfolio": 100
    },
    {
      "caller": "Brook \ud83d\udc80\ud83e\uddf2",
      "totalCalls": 186,
      "uniqueTokens": 174,
      "totalTrades": 135,
      "winRate": 48.888888888888886,
      "winningTrades": 66,
      "losingTrades": 69,
      "avgPnlPerTrade": 3.3062718846757546,
      "finalPortfolio": 152.9383767813608,
      "compoundFactor": 1.529383767813608,
      "simpleFinalPortfolio": 144.63467044312267,
      "simpleReturnPercent": 44.63467044312268,
      "initialPortfolio": 100
    },
    {
      "caller": "Pigoshi \ud83d\udc3d \ud83e\uddb4\ufe0f",
      "totalCalls": 22,
      "uniqueTokens": 22,
      "totalTrades": 9,
      "winRate": 44.44444444444444,
      "winningTrades": 4,
      "losingTrades": 5,
      "avgPnlPerTrade": 53.97849358628737,
      "finalPortfolio": 148.30721362763563,
      "compoundFactor": 1.4830721362763564,
      "simpleFinalPortfolio": 148.58064422765864,
      "simpleReturnPercent": 48.580644227658645,
      "initialPortfolio": 100
    },
    {
      "caller": "Prometheus",
      "totalCalls": 52,
      "uniqueTokens": 52,
      "totalTrades": 50,
      "winRate": 50,
      "winningTrades": 25,
      "losingTrades": 25,
      "avgPnlPerTrade": 7.955767432699607,
      "finalPortfolio": 145.93851278934858,
      "compoundFactor": 1.4593851278934857,
      "simpleFinalPortfolio": 139.77883716349803,
      "simpleReturnPercent": 39.77883716349802,
      "initialPortfolio": 100
    },
    {
      "caller": "Mac (rari rizz Arc)",
      "totalCalls": 93,
      "uniqueTokens": 90,
      "totalTrades": 72,
      "winRate": 38.88888888888889,
      "winningTrades": 28,
      "losingTrades": 44,
      "avgPnlPerTrade": 5.280121627924602,
      "finalPortfolio": 142.6814669170519,
      "compoundFactor": 1.426814669170519,
      "simpleFinalPortfolio": 138.01687572105715,
      "simpleReturnPercent": 38.01687572105714,
      "initialPortfolio": 100
    },
    {
      "caller": "RektBigHustla | @OurCryptoHood Owner",
      "totalCalls": 46,
      "uniqueTokens": 41,
      "totalTrades": 25,
      "winRate": 52,
      "winningTrades": 13,
      "losingTrades": 12,
      "avgPnlPerTrade": 16.445188535854825,
      "finalPortfolio": 142.51388382344683,
      "compoundFactor": 1.4251388382344683,
      "simpleFinalPortfolio": 141.11297133963706,
      "simpleReturnPercent": 41.11297133963705,
      "initialPortfolio": 100
    },
    {
      "caller": "rastaland.TV",
      "totalCalls": 68,
      "uniqueTokens": 60,
      "totalTrades": 57,
      "winRate": 52.63157894736842,
      "winningTrades": 30,
      "losingTrades": 27,
      "avgPnlPerTrade": 5.996509858680488,
      "finalPortfolio": 136.69747531195077,
      "compoundFactor": 1.3669747531195078,
      "simpleFinalPortfolio": 134.18010619447875,
      "simpleReturnPercent": 34.18010619447875,
      "initialPortfolio": 100
    },
    {
      "caller": "JK -Whale",
      "totalCalls": 84,
      "uniqueTokens": 83,
      "totalTrades": 67,
      "winRate": 49.25373134328358,
      "winningTrades": 33,
      "losingTrades": 34,
      "avgPnlPerTrade": 4.858163846394346,
      "finalPortfolio": 134.29899522138703,
      "compoundFactor": 1.3429899522138704,
      "simpleFinalPortfolio": 132.54969777084213,
      "simpleReturnPercent": 32.54969777084214,
      "initialPortfolio": 100
    },
    {
      "caller": "Whale \ud83d\udc33 x",
      "totalCalls": 78,
      "uniqueTokens": 76,
      "totalTrades": 62,
      "winRate": 51.61290322580645,
      "winningTrades": 32,
      "losingTrades": 30,
      "avgPnlPerTrade": 3.623195437254219,
      "finalPortfolio": 122.72157196112215,
      "compoundFactor": 1.2272157196112214,
      "simpleFinalPortfolio": 122.46381171097613,
      "simpleReturnPercent": 22.463811710976135,
      "initialPortfolio": 100
    },
    {
      "caller": "Mr Scarface",
      "totalCalls": 22,
      "uniqueTokens": 21,
      "totalTrades": 19,
      "winRate": 52.63157894736842,
      "winningTrades": 10,
      "losingTrades": 9,
      "avgPnlPerTrade": 9.924754688390736,
      "finalPortfolio": 119.81405313068217,
      "compoundFactor": 1.1981405313068216,
      "simpleFinalPortfolio": 118.8570339079424,
      "simpleReturnPercent": 18.8570339079424,
      "initialPortfolio": 100
    },
    {
      "caller": "Rayin \u96f7\u97f3",
      "totalCalls": 40,
      "uniqueTokens": 39,
      "totalTrades": 23,
      "winRate": 39.130434782608695,
      "winningTrades": 9,
      "losingTrades": 14,
      "avgPnlPerTrade": 5.486571983061815,
      "finalPortfolio": 113.00226591764297,
      "compoundFactor": 1.1300226591764297,
      "simpleFinalPortfolio": 112.61911556104218,
      "simpleReturnPercent": 12.619115561042182,
      "initialPortfolio": 100
    },
    {
      "caller": "Rayin",
      "totalCalls": 47,
      "uniqueTokens": 42,
      "totalTrades": 24,
      "winRate": 33.33333333333333,
      "winningTrades": 8,
      "losingTrades": 16,
      "avgPnlPerTrade": 5.022226407703443,
      "finalPortfolio": 112.37239160034297,
      "compoundFactor": 1.1237239160034296,
      "simpleFinalPortfolio": 112.05334337848826,
      "simpleReturnPercent": 12.053343378488268,
      "initialPortfolio": 100
    },
    {
      "caller": "Argy",
      "totalCalls": 2,
      "uniqueTokens": 2,
      "totalTrades": 2,
      "winRate": 50,
      "winningTrades": 1,
      "losingTrades": 1,
      "avgPnlPerTrade": 42.86174897637509,
      "finalPortfolio": 108.54564531019743,
      "compoundFactor": 1.0854564531019744,
      "simpleFinalPortfolio": 108.57234979527502,
      "simpleReturnPercent": 8.572349795275013,
      "initialPortfolio": 100
    },
    {
      "caller": "Salvatore \ud83e\udd87 |Genius|",
      "totalCalls": 17,
      "uniqueTokens": 17,
      "totalTrades": 14,
      "winRate": 42.857142857142854,
      "winningTrades": 6,
      "losingTrades": 8,
      "avgPnlPerTrade": 6.2280309459707,
      "finalPortfolio": 108.49484367874557,
      "compoundFactor": 1.0849484367874558,
      "simpleFinalPortfolio": 108.71924332435898,
      "simpleReturnPercent": 8.719243324358983,
      "initialPortfolio": 100
    },
    {
      "caller": "Marsel Ellada",
      "totalCalls": 33,
      "uniqueTokens": 31,
      "totalTrades": 21,
      "winRate": 47.61904761904761,
      "winningTrades": 10,
      "losingTrades": 11,
      "avgPnlPerTrade": 3.5303325129335095,
      "finalPortfolio": 107.50821786066187,
      "compoundFactor": 1.0750821786066187,
      "simpleFinalPortfolio": 107.41369827716036,
      "simpleReturnPercent": 7.413698277160363,
      "initialPortfolio": 100
    },
    {
      "caller": "Degens",
      "totalCalls": 7,
      "uniqueTokens": 7,
      "totalTrades": 6,
      "winRate": 83.33333333333334,
      "winningTrades": 5,
      "losingTrades": 1,
      "avgPnlPerTrade": 12.170520852751338,
      "finalPortfolio": 107.3869585732193,
      "compoundFactor": 1.073869585732193,
      "simpleFinalPortfolio": 107.3023125116508,
      "simpleReturnPercent": 7.302312511650788,
      "initialPortfolio": 100
    },
    {
      "caller": "Min Min",
      "totalCalls": 17,
      "uniqueTokens": 17,
      "totalTrades": 13,
      "winRate": 69.23076923076923,
      "winningTrades": 9,
      "losingTrades": 4,
      "avgPnlPerTrade": 4.010512012017372,
      "finalPortfolio": 105.23576776211453,
      "compoundFactor": 1.0523576776211454,
      "simpleFinalPortfolio": 105.21366561562259,
      "simpleReturnPercent": 5.213665615622598,
      "initialPortfolio": 100
    },
    {
      "caller": "H B",
      "totalCalls": 3,
      "uniqueTokens": 3,
      "totalTrades": 3,
      "winRate": 100,
      "winningTrades": 3,
      "losingTrades": 0,
      "avgPnlPerTrade": 17.190486025434705,
      "finalPortfolio": 105.17711919410426,
      "compoundFactor": 1.0517711919410426,
      "simpleFinalPortfolio": 105.15714580763041,
      "simpleReturnPercent": 5.157145807630403,
      "initialPortfolio": 100
    },
    {
      "caller": "AnnaGems\ufe0f (multi-chain)",
      "totalCalls": 15,
      "uniqueTokens": 15,
      "totalTrades": 3,
      "winRate": 100,
      "winningTrades": 3,
      "losingTrades": 0,
      "avgPnlPerTrade": 12.104749333303388,
      "finalPortfolio": 103.63230809884212,
      "compoundFactor": 1.0363230809884212,
      "simpleFinalPortfolio": 103.63142479999101,
      "simpleReturnPercent": 3.631424799991012,
      "initialPortfolio": 100
    },
    {
      "caller": "Cobalt",
      "totalCalls": 12,
      "uniqueTokens": 10,
      "totalTrades": 6,
      "winRate": 33.33333333333333,
      "winningTrades": 2,
      "losingTrades": 4,
      "avgPnlPerTrade": 6.13730000507132,
      "finalPortfolio": 103.61202429492752,
      "compoundFactor": 1.0361202429492753,
      "simpleFinalPortfolio": 103.6823800030428,
      "simpleReturnPercent": 3.6823800030427956,
      "initialPortfolio": 100
    },
    {
      "caller": "\u029f \u1d07 \u1d0d \u1d0f \u0274 \u1d04 \u029c \u026a \u029f \u1d05 \ud83c\udf4b",
      "totalCalls": 6,
      "uniqueTokens": 6,
      "totalTrades": 2,
      "winRate": 100,
      "winningTrades": 2,
      "losingTrades": 0,
      "avgPnlPerTrade": 16.44165067997817,
      "finalPortfolio": 103.2905466569372,
      "compoundFactor": 1.032905466569372,
      "simpleFinalPortfolio": 103.28833013599564,
      "simpleReturnPercent": 3.288330135995632,
      "initialPortfolio": 100
    },
    {
      "caller": "Crypto BO$$ \ud83d\udc80",
      "totalCalls": 7,
      "uniqueTokens": 7,
      "totalTrades": 6,
      "winRate": 50,
      "winningTrades": 3,
      "losingTrades": 3,
      "avgPnlPerTrade": 5.486849354588569,
      "finalPortfolio": 103.27427613485092,
      "compoundFactor": 1.0327427613485092,
      "simpleFinalPortfolio": 103.29210961275314,
      "simpleReturnPercent": 3.292109612753147,
      "initialPortfolio": 100
    },
    {
      "caller": "meme world order",
      "totalCalls": 25,
      "uniqueTokens": 24,
      "totalTrades": 16,
      "winRate": 43.75,
      "winningTrades": 7,
      "losingTrades": 9,
      "avgPnlPerTrade": 1.9108568796653993,
      "finalPortfolio": 102.87797758969488,
      "compoundFactor": 1.0287797758969488,
      "simpleFinalPortfolio": 103.05737100746464,
      "simpleReturnPercent": 3.0573710074646376,
      "initialPortfolio": 100
    },
    {
      "caller": "BlockBard @Mrcrypt100xcalls",
      "totalCalls": 1,
      "uniqueTokens": 1,
      "totalTrades": 1,
      "winRate": 100,
      "winningTrades": 1,
      "losingTrades": 0,
      "avgPnlPerTrade": 27.2982782597742,
      "finalPortfolio": 102.72982782597742,
      "compoundFactor": 1.0272982782597742,
      "simpleFinalPortfolio": 102.72982782597742,
      "simpleReturnPercent": 2.7298278259774156,
      "initialPortfolio": 100
    },
    {
      "caller": "KungFuDOOM (DOOM arc)",
      "totalCalls": 7,
      "uniqueTokens": 7,
      "totalTrades": 5,
      "winRate": 40,
      "winningTrades": 2,
      "losingTrades": 3,
      "avgPnlPerTrade": 4.490738126385825,
      "finalPortfolio": 102.24070328785359,
      "compoundFactor": 1.022407032878536,
      "simpleFinalPortfolio": 102.24536906319291,
      "simpleReturnPercent": 2.2453690631929035,
      "initialPortfolio": 100
    },
    {
      "caller": "Jewel.Sol",
      "totalCalls": 6,
      "uniqueTokens": 6,
      "totalTrades": 6,
      "winRate": 33.33333333333333,
      "winningTrades": 2,
      "losingTrades": 4,
      "avgPnlPerTrade": 2.7651921625874487,
      "finalPortfolio": 101.6596594662884,
      "compoundFactor": 1.016596594662884,
      "simpleFinalPortfolio": 101.65911529755247,
      "simpleReturnPercent": 1.6591152975524714,
      "initialPortfolio": 100
    },
    {
      "caller": "Zephyr (Back 10/25)",
      "totalCalls": 4,
      "uniqueTokens": 4,
      "totalTrades": 2,
      "winRate": 100,
      "winningTrades": 2,
      "losingTrades": 0,
      "avgPnlPerTrade": 4.967402744539562,
      "finalPortfolio": 100.99389857014692,
      "compoundFactor": 1.0099389857014693,
      "simpleFinalPortfolio": 100.99348054890791,
      "simpleReturnPercent": 0.9934805489079102,
      "initialPortfolio": 100
    },
    {
      "caller": "Zephyr",
      "totalCalls": 6,
      "uniqueTokens": 6,
      "totalTrades": 3,
      "winRate": 66.66666666666666,
      "winningTrades": 2,
      "losingTrades": 1,
      "avgPnlPerTrade": 2.6511792734554023,
      "finalPortfolio": 100.79505410578462,
      "compoundFactor": 1.0079505410578462,
      "simpleFinalPortfolio": 100.79535378203661,
      "simpleReturnPercent": 0.7953537820366119,
      "initialPortfolio": 100
    },
    {
      "caller": "\ud83e\udd35\ud83c\udf4cMr Banana\ud83c\udf4c\ud83e\udd35.\u08e9\u08e9",
      "totalCalls": 3,
      "uniqueTokens": 3,
      "totalTrades": 3,
      "winRate": 66.66666666666666,
      "winningTrades": 2,
      "losingTrades": 1,
      "avgPnlPerTrade": 2.2227214111794695,
      "finalPortfolio": 100.6664421084719,
      "compoundFactor": 1.0066644210847189,
      "simpleFinalPortfolio": 100.66681642335384,
      "simpleReturnPercent": 0.6668164233538443,
      "initialPortfolio": 100
    },
    {
      "caller": "Gidion",
      "totalCalls": 7,
      "uniqueTokens": 5,
      "totalTrades": 4,
      "winRate": 50,
      "winningTrades": 2,
      "losingTrades": 2,
      "avgPnlPerTrade": 1.2473530542653681,
      "finalPortfolio": 100.49553572842407,
      "compoundFactor": 1.0049553572842407,
      "simpleFinalPortfolio": 100.49894122170615,
      "simpleReturnPercent": 0.49894122170615063,
      "initialPortfolio": 100
    },
    {
      "caller": "soru",
      "totalCalls": 8,
      "uniqueTokens": 5,
      "totalTrades": 3,
      "winRate": 33.33333333333333,
      "winningTrades": 1,
      "losingTrades": 2,
      "avgPnlPerTrade": 1.3042766022737906,
      "finalPortfolio": 100.387929978715,
      "compoundFactor": 1.00387929978715,
      "simpleFinalPortfolio": 100.39128298068213,
      "simpleReturnPercent": 0.3912829806821394,
      "initialPortfolio": 100
    },
    {
      "caller": "MITCHI | RDGN",
      "totalCalls": 3,
      "uniqueTokens": 2,
      "totalTrades": 2,
      "winRate": 50,
      "winningTrades": 1,
      "losingTrades": 1,
      "avgPnlPerTrade": 1.8580871376897845,
      "finalPortfolio": 100.35309346628011,
      "compoundFactor": 1.0035309346628012,
      "simpleFinalPortfolio": 100.37161742753796,
      "simpleReturnPercent": 0.37161742753795135,
      "initialPortfolio": 100
    },
    {
      "caller": "S\"atoshis'sun Sa",
      "totalCalls": 1,
      "uniqueTokens": 1,
      "totalTrades": 1,
      "winRate": 100,
      "winningTrades": 1,
      "losingTrades": 0,
      "avgPnlPerTrade": 2.5816483763647424,
      "finalPortfolio": 100.25816483763647,
      "compoundFactor": 1.0025816483763648,
      "simpleFinalPortfolio": 100.25816483763647,
      "simpleReturnPercent": 0.25816483763647646,
      "initialPortfolio": 100
    },
    {
      "caller": "Italian Hunter\ud83d\udc0a ~ \u6cd5\u96f7\u5229 ~ \ud83d\udd25",
      "totalCalls": 4,
      "uniqueTokens": 4,
      "totalTrades": 4,
      "winRate": 75,
      "winningTrades": 3,
      "losingTrades": 1,
      "avgPnlPerTrade": 0.4440168418652135,
      "finalPortfolio": 100.1773581219084,
      "compoundFactor": 1.001773581219084,
      "simpleFinalPortfolio": 100.17760673674609,
      "simpleReturnPercent": 0.17760673674609428,
      "initialPortfolio": 100
    },
    {
      "caller": "Simple | MAXI",
      "totalCalls": 4,
      "uniqueTokens": 4,
      "totalTrades": 2,
      "winRate": 50,
      "winningTrades": 1,
      "losingTrades": 1,
      "avgPnlPerTrade": 0.8604741594734122,
      "finalPortfolio": 100.17209483189468,
      "compoundFactor": 1.0017209483189469,
      "simpleFinalPortfolio": 100.17209483189468,
      "simpleReturnPercent": 0.17209483189468688,
      "initialPortfolio": 100
    },
    {
      "caller": "Joe",
      "totalCalls": 1,
      "uniqueTokens": 1,
      "totalTrades": 1,
      "winRate": 100,
      "winningTrades": 1,
      "losingTrades": 0,
      "avgPnlPerTrade": 1.2141075652206013,
      "finalPortfolio": 100.12141075652207,
      "compoundFactor": 1.0012141075652208,
      "simpleFinalPortfolio": 100.12141075652207,
      "simpleReturnPercent": 0.12141075652207789,
      "initialPortfolio": 100
    },
    {
      "caller": "Bishop (Slow DMs)",
      "totalCalls": 1,
      "uniqueTokens": 1,
      "totalTrades": 1,
      "winRate": 100,
      "winningTrades": 1,
      "losingTrades": 0,
      "avgPnlPerTrade": 0.5418657881169464,
      "finalPortfolio": 100.0541865788117,
      "compoundFactor": 1.0005418657881169,
      "simpleFinalPortfolio": 100.0541865788117,
      "simpleReturnPercent": 0.05418657881168798,
      "initialPortfolio": 100
    },
    {
      "caller": "Phillip (PhillipsCalls)\ud83c\udde6\ud83c\uddea",
      "totalCalls": 1,
      "uniqueTokens": 1,
      "totalTrades": 1,
      "winRate": 100,
      "winningTrades": 1,
      "losingTrades": 0,
      "avgPnlPerTrade": 0.34303020467618683,
      "finalPortfolio": 100.03430302046762,
      "compoundFactor": 1.000343030204676,
      "simpleFinalPortfolio": 100.03430302046762,
      "simpleReturnPercent": 0.03430302046760758,
      "initialPortfolio": 100
    },
    {
      "caller": "fred",
      "totalCalls": 2,
      "uniqueTokens": 2,
      "totalTrades": 1,
      "winRate": 100,
      "winningTrades": 1,
      "losingTrades": 0,
      "avgPnlPerTrade": 0.28122123785614406,
      "finalPortfolio": 100.02812212378561,
      "compoundFactor": 1.000281221237856,
      "simpleFinalPortfolio": 100.02812212378561,
      "simpleReturnPercent": 0.028122123785601083,
      "initialPortfolio": 100
    },
    {
      "caller": "TrenchRadar Scanner",
      "totalCalls": 1,
      "uniqueTokens": 1,
      "totalTrades": 1,
      "winRate": 0,
      "winningTrades": 0,
      "losingTrades": 1,
      "avgPnlPerTrade": 0,
      "finalPortfolio": 100,
      "compoundFactor": 1,
      "simpleFinalPortfolio": 100,
      "simpleReturnPercent": 0,
      "initialPortfolio": 100
    },
    {
      "caller": "God Everything",
      "totalCalls": 7,
      "uniqueTokens": 7,
      "totalTrades": 1,
      "winRate": 0,
      "winningTrades": 0,
      "losingTrades": 1,
      "avgPnlPerTrade": 0,
      "finalPortfolio": 100,
      "compoundFactor": 1,
      "simpleFinalPortfolio": 100,
      "simpleReturnPercent": 0,
      "initialPortfolio": 100
    },
    {
      "caller": "Felix",
      "totalCalls": 1,
      "uniqueTokens": 1,
      "totalTrades": 1,
      "winRate": 0,
      "winningTrades": 0,
      "losingTrades": 1,
      "avgPnlPerTrade": 0,
      "finalPortfolio": 100,
      "compoundFactor": 1,
      "simpleFinalPortfolio": 100,
      "simpleReturnPercent": 0,
      "initialPortfolio": 100
    },
    {
      "caller": "Khing\ud83d\udc51 | @khingcallsgem",
      "totalCalls": 2,
      "uniqueTokens": 2,
      "totalTrades": 2,
      "winRate": 50,
      "winningTrades": 1,
      "losingTrades": 1,
      "avgPnlPerTrade": -0.17947831276759474,
      "finalPortfolio": 99.96399159056396,
      "compoundFactor": 0.9996399159056396,
      "simpleFinalPortfolio": 99.96410433744649,
      "simpleReturnPercent": -0.035895662553508956,
      "initialPortfolio": 100
    },
    {
      "caller": "terr\u00f8r",
      "totalCalls": 1,
      "uniqueTokens": 1,
      "totalTrades": 1,
      "winRate": 0,
      "winningTrades": 0,
      "losingTrades": 1,
      "avgPnlPerTrade": -0.5569514722997382,
      "finalPortfolio": 99.94430485277003,
      "compoundFactor": 0.9994430485277003,
      "simpleFinalPortfolio": 99.94430485277003,
      "simpleReturnPercent": -0.05569514722997271,
      "initialPortfolio": 100
    },
    {
      "caller": "Zephyr (AFK 3 DAYS)",
      "totalCalls": 1,
      "uniqueTokens": 1,
      "totalTrades": 1,
      "winRate": 0,
      "winningTrades": 0,
      "losingTrades": 1,
      "avgPnlPerTrade": -1.981267668712916,
      "finalPortfolio": 99.8018732331287,
      "compoundFactor": 0.998018732331287,
      "simpleFinalPortfolio": 99.8018732331287,
      "simpleReturnPercent": -0.19812676687129827,
      "initialPortfolio": 100
    },
    {
      "caller": "Checkma1e \u265f\ufe0f",
      "totalCalls": 1,
      "uniqueTokens": 1,
      "totalTrades": 1,
      "winRate": 0,
      "winningTrades": 0,
      "losingTrades": 1,
      "avgPnlPerTrade": -7.891153581165722,
      "finalPortfolio": 99.21088464188342,
      "compoundFactor": 0.9921088464188342,
      "simpleFinalPortfolio": 99.21088464188342,
      "simpleReturnPercent": -0.7891153581165766,
      "initialPortfolio": 100
    },
    {
      "caller": "Xebek",
      "totalCalls": 34,
      "uniqueTokens": 26,
      "totalTrades": 2,
      "winRate": 0,
      "winningTrades": 0,
      "losingTrades": 2,
      "avgPnlPerTrade": -3.9539151462635482,
      "finalPortfolio": 99.20988058650134,
      "compoundFactor": 0.9920988058650134,
      "simpleFinalPortfolio": 99.20921697074729,
      "simpleReturnPercent": -0.7907830292527063,
      "initialPortfolio": 100
    },
    {
      "caller": "Dr.Monad Malik",
      "totalCalls": 4,
      "uniqueTokens": 4,
      "totalTrades": 4,
      "winRate": 50,
      "winningTrades": 2,
      "losingTrades": 2,
      "avgPnlPerTrade": -2.1304633992993036,
      "finalPortfolio": 99.14188354420374,
      "compoundFactor": 0.9914188354420373,
      "simpleFinalPortfolio": 99.14781464028027,
      "simpleReturnPercent": -0.852185359719726,
      "initialPortfolio": 100
    },
    {
      "caller": "Ivan Syah",
      "totalCalls": 3,
      "uniqueTokens": 3,
      "totalTrades": 1,
      "winRate": 0,
      "winningTrades": 0,
      "losingTrades": 1,
      "avgPnlPerTrade": -8.66893722077846,
      "finalPortfolio": 99.13310627792215,
      "compoundFactor": 0.9913310627792216,
      "simpleFinalPortfolio": 99.13310627792215,
      "simpleReturnPercent": -0.8668937220778439,
      "initialPortfolio": 100
    },
    {
      "caller": "Stefan",
      "totalCalls": 4,
      "uniqueTokens": 3,
      "totalTrades": 3,
      "winRate": 66.66666666666666,
      "winningTrades": 2,
      "losingTrades": 1,
      "avgPnlPerTrade": -4.269743544521595,
      "finalPortfolio": 98.71772861581552,
      "compoundFactor": 0.9871772861581551,
      "simpleFinalPortfolio": 98.71907693664352,
      "simpleReturnPercent": -1.2809230633564872,
      "initialPortfolio": 100
    },
    {
      "caller": "Goons\ud83e\uddf2 \ud80c\udcf5",
      "totalCalls": 12,
      "uniqueTokens": 10,
      "totalTrades": 3,
      "winRate": 66.66666666666666,
      "winningTrades": 2,
      "losingTrades": 1,
      "avgPnlPerTrade": -4.31193389022528,
      "finalPortfolio": 98.70236430822789,
      "compoundFactor": 0.9870236430822789,
      "simpleFinalPortfolio": 98.70641983293241,
      "simpleReturnPercent": -1.2935801670675873,
      "initialPortfolio": 100
    },
    {
      "caller": "Badass [ WON\u2019T DM FIRST ]",
      "totalCalls": 4,
      "uniqueTokens": 3,
      "totalTrades": 3,
      "winRate": 0,
      "winningTrades": 0,
      "losingTrades": 3,
      "avgPnlPerTrade": -6.653064960611232,
      "finalPortfolio": 98.00739101106453,
      "compoundFactor": 0.9800739101106453,
      "simpleFinalPortfolio": 98.00408051181662,
      "simpleReturnPercent": -1.995919488183373,
      "initialPortfolio": 100
    },
    {
      "caller": "Kuzgun",
      "totalCalls": 3,
      "uniqueTokens": 2,
      "totalTrades": 2,
      "winRate": 0,
      "winningTrades": 0,
      "losingTrades": 2,
      "avgPnlPerTrade": -10.78724656872147,
      "finalPortfolio": 97.8442912897998,
      "compoundFactor": 0.978442912897998,
      "simpleFinalPortfolio": 97.8425506862557,
      "simpleReturnPercent": -2.1574493137442974,
      "initialPortfolio": 100
    }
  ]
}